Metadata-Version: 1.0
Name: stl-tools
Version: 0.2.1
Summary: Generate STL files from numpy arrays and text
Home-page: https://github.com/thearn/stl_tools
Author: Tristan Hearn
Author-email: tristanhearn@gmail.com
License: Apache 2.0
Platform: UNKNOWN
